timesformer_pytorch/__init__.py
timesformer_pytorch/rotary.py
timesformer_pytorch/timesformer_pytorch.py
timesformer_pytorch-0.4.1.dist-info/LICENSE
timesformer_pytorch-0.4.1.dist-info/METADATA
timesformer_pytorch-0.4.1.dist-info/WHEEL
timesformer_pytorch-0.4.1.dist-info/top_level.txt
timesformer_pytorch-0.4.1.dist-info/RECORD
